jsonpickle/__init__.py
jsonpickle/backend.py
jsonpickle/compat.py
jsonpickle/errors.py
jsonpickle/handlers.py
jsonpickle/pickler.py
jsonpickle/tags.py
jsonpickle/tags_pd.py
jsonpickle/unpickler.py
jsonpickle/util.py
jsonpickle/version.py
jsonpickle/ext/__init__.py
jsonpickle/ext/gmpy.py
jsonpickle/ext/numpy.py
jsonpickle/ext/pandas.py
jsonpickle-4.0.4.dist-info/LICENSE
jsonpickle-4.0.4.dist-info/METADATA
jsonpickle-4.0.4.dist-info/WHEEL
jsonpickle-4.0.4.dist-info/top_level.txt
jsonpickle-4.0.4.dist-info/RECORD
